cdk_data_zone/__init__.py
cdk_data_zone/py.typed
cdk_data_zone/_jsii/__init__.py
cdk_data_zone/_jsii/cdk-data-zone@0.0.3.jsii.tgz
cdk_data_zone-0.0.3.dist-info/LICENSE
cdk_data_zone-0.0.3.dist-info/METADATA
cdk_data_zone-0.0.3.dist-info/WHEEL
cdk_data_zone-0.0.3.dist-info/top_level.txt
cdk_data_zone-0.0.3.dist-info/RECORD
